dataserver/__init__.py
dataserver/client.py
dataserver/server.py
dataserver-1.0.1.dist-info/LICENSE
dataserver-1.0.1.dist-info/METADATA
dataserver-1.0.1.dist-info/WHEEL
dataserver-1.0.1.dist-info/top_level.txt
dataserver-1.0.1.dist-info/RECORD
