Metadata-Version: 2.1
Name: dataserver
Version: 1.0.1
Summary: A free to use dataserver for everyone
Author-email: Nguyen Minh Khoi <khoi.nguyenminh100912@gmail.com>
Project-URL: Homepage, https://github.com/pypa/dataserver
Project-URL: Issues, https://github.com/pypa/dataserver/issues
Classifier: Programming Language :: Python :: 3
Classifier: License :: OSI Approved :: MIT License
Classifier: Operating System :: OS Independent
Requires-Python: >=3
License-File: LICENSE
